ScanImageTiffReader/__init__.py
ScanImageTiffReader/external/README.md
ScanImageTiffReader/external/__init__.py
ScanImageTiffReader/external/ScanImageTiffReader-1.4.1-Darwin/lib/libScanImageTiffReaderAPI.so
ScanImageTiffReader/external/ScanImageTiffReader-1.4.1-Darwin-arm64/lib/libScanImageTiffReaderAPI.so
ScanImageTiffReader/external/ScanImageTiffReader-1.4.1-Linux/lib/libScanImageTiffReaderAPI.so
ScanImageTiffReader/external/ScanImageTiffReader-1.4.1-win64/lib/ScanImageTiffReaderAPI.dll
scanimage_tiff_reader-1.4.1.4.dist-info/LICENSE
scanimage_tiff_reader-1.4.1.4.dist-info/METADATA
scanimage_tiff_reader-1.4.1.4.dist-info/WHEEL
scanimage_tiff_reader-1.4.1.4.dist-info/entry_points.txt
scanimage_tiff_reader-1.4.1.4.dist-info/top_level.txt
scanimage_tiff_reader-1.4.1.4.dist-info/RECORD
