Metadata-Version: 2.1
Name: scanimage-tiff-reader
Version: 1.4.1.4
Summary: A fast (big)tiff reader that provides access to ScanImage-specific metadata.
Author: Nathan Clack
Maintainer-email: Lawrence Niu <lawrence@mbfbioscience.com>, Nelson Downs <nelson@mbfbioscience.com>, MBF Support <support@mbfbioscience.com>
License: Copyright (C) 2023 MBF Bioscience
Project-URL: repository, https://gitlab.com/vidriotech/scanimagetiffreader-python
Project-URL: documentation, https://vidriotech.gitlab.io/scanimagetiffreader-python
Classifier: Programming Language :: Python :: 3
Classifier: License :: OSI Approved :: Apache Software License
Classifier: Operating System :: Microsoft :: Windows
Classifier: Operating System :: POSIX
Classifier: Operating System :: MacOS :: MacOS X
Classifier: Environment :: MacOS X
Classifier: Environment :: Win32 (MS Windows)
Classifier: Topic :: Scientific/Engineering
Classifier: Development Status :: 5 - Production/Stable
Requires-Python: >=3.7
License-File: LICENSE
Requires-Dist: numpy
